workcraft/__init__.py
workcraft/__main__.py
workcraft/models.py
workcraft/peon.py
workcraft/utils.py
workcraft_peon-0.1.18.dist-info/METADATA
workcraft_peon-0.1.18.dist-info/WHEEL
workcraft_peon-0.1.18.dist-info/RECORD
