Metadata-Version: 2.4
Name: workcraft-peon
Version: 0.1.18
Summary: The worker library that eats celery for breakfast
Requires-Python: >=3.10
Requires-Dist: beartype>=0.19.0
Requires-Dist: fire>=0.7.0
Requires-Dist: loguru>=0.7.3
Requires-Dist: pydantic>=2.10.3
Requires-Dist: requests>=2.32.3
Requires-Dist: tenacity>=9.0.0
Requires-Dist: websockets>=14.1
